boxfish/VERSION
boxfish/__init__.py
boxfish/__main__.py
boxfish/data/__init__.py
boxfish/data/config.py
boxfish/data/soups.py
boxfish/data/website.py
boxfish/utils/__init__.py
boxfish/utils/dataframes.py
boxfish/utils/dicts.py
boxfish/utils/drivers.py
boxfish/utils/lists.py
boxfish/utils/strings.py
boxfish/utils/times.py
boxfish/utils/urls.py
boxfish/utils/utils.py
boxfish/utils/xpaths.py
boxfish-0.1.2.dist-info/LICENSE
boxfish-0.1.2.dist-info/METADATA
boxfish-0.1.2.dist-info/WHEEL
boxfish-0.1.2.dist-info/top_level.txt
boxfish-0.1.2.dist-info/RECORD
