Metadata-Version: 2.1
Name: boxfish
Version: 0.1.2
Summary: A lightweight tool for table extraction from HTML pages.
Home-page: https://github.com/peterkorteweg/boxfish/
Author: Peter Korteweg
Author-email: boxfish@peterkorteweg.com
License: MIT
Keywords: beautifulsoup html pandas scraping tables
Platform: UNKNOWN
Classifier: Development Status :: 3 - Alpha
Classifier: License :: OSI Approved :: MIT License
Classifier: Programming Language :: Python :: 3
Classifier: Programming Language :: Python :: 3.6
Classifier: Programming Language :: Python :: 3.7
Classifier: Programming Language :: Python :: 3.8
Classifier: Programming Language :: Python :: 3.9
Requires-Python: >=3.6
License-File: LICENSE
Requires-Dist: requests
Requires-Dist: beautifulsoup4
Requires-Dist: selenium
Requires-Dist: lxml
